MANIFEST.in
README.rst
setup.cfg
setup.py
tw2/__init__.py
tw2.jqplugins.elfinder.egg-info/PKG-INFO
tw2.jqplugins.elfinder.egg-info/SOURCES.txt
tw2.jqplugins.elfinder.egg-info/dependency_links.txt
tw2.jqplugins.elfinder.egg-info/entry_points.txt
tw2.jqplugins.elfinder.egg-info/namespace_packages.txt
tw2.jqplugins.elfinder.egg-info/not-zip-safe
tw2.jqplugins.elfinder.egg-info/requires.txt
tw2.jqplugins.elfinder.egg-info/top_level.txt
tw2/jqplugins/__init__.py
tw2/jqplugins/elfinder/__init__.py
tw2/jqplugins/elfinder/base.py
tw2/jqplugins/elfinder/defaults.py
tw2/jqplugins/elfinder/samples.py
tw2/jqplugins/elfinder/widgets.py
tw2/jqplugins/elfinder/connector/__init__.py
tw2/jqplugins/elfinder/connector/cgi.py
tw2/jqplugins/elfinder/connector/elFinder.py
tw2/jqplugins/elfinder/static/jquery/plugins/elfinder/1.1/Changelog
tw2/jqplugins/elfinder/static/jquery/plugins/elfinder/1.1/README
tw2/jqplugins/elfinder/static/jquery/plugins/elfinder/1.1/elfinder.php.html
tw2/jqplugins/elfinder/static/jquery/plugins/elfinder/1.1/connectors/php/connector.php
tw2/jqplugins/elfinder/static/jquery/plugins/elfinder/1.1/connectors/php/elFinder.class.php
tw2/jqplugins/elfinder/static/jquery/plugins/elfinder/1.1/connectors/python/connector.py
tw2/jqplugins/elfinder/static/jquery/plugins/elfinder/1.1/connectors/python/elFinder.py
tw2/jqplugins/elfinder/static/jquery/plugins/elfinder/1.1/css/elfinder.css
tw2/jqplugins/elfinder/static/jquery/plugins/elfinder/1.1/images/icons-big.png
tw2/jqplugins/elfinder/static/jquery/plugins/elfinder/1.1/images/icons-small.png
tw2/jqplugins/elfinder/static/jquery/plugins/elfinder/1.1/images/ql.png
tw2/jqplugins/elfinder/static/jquery/plugins/elfinder/1.1/images/spinner.gif
tw2/jqplugins/elfinder/static/jquery/plugins/elfinder/1.1/images/toolbar.png
tw2/jqplugins/elfinder/static/jquery/plugins/elfinder/1.1/js/elfinder.full.js
tw2/jqplugins/elfinder/static/jquery/plugins/elfinder/1.1/js/elfinder.min.js
tw2/jqplugins/elfinder/static/jquery/plugins/elfinder/1.1/js/jquery-1.3.2.min.js
tw2/jqplugins/elfinder/static/jquery/plugins/elfinder/1.1/js/jquery-1.4.1.min.js
tw2/jqplugins/elfinder/static/jquery/plugins/elfinder/1.1/js/jquery-ui-1.7.2.custom.min.js
tw2/jqplugins/elfinder/static/jquery/plugins/elfinder/1.1/js/jquery-ui-1.8b1.min.js
tw2/jqplugins/elfinder/static/jquery/plugins/elfinder/1.1/js/i18n/elfinder.es.js
